g_gantt/__init__.py
g_gantt/main.py
g_gantt/test.py
g_gantt-0.1.11.dist-info/LICENSE
g_gantt-0.1.11.dist-info/METADATA
g_gantt-0.1.11.dist-info/WHEEL
g_gantt-0.1.11.dist-info/top_level.txt
g_gantt-0.1.11.dist-info/RECORD
