Metadata-Version: 2.1
Name: g_gantt
Version: 0.1.11
Summary: A Pythonic way to make Gantt Charts based off the Google Chart Gantt Chart html/JS charting library
Author: Brady Golomb
License: MIT
Project-URL: Repository, https://github.com/bagolomb/g_gantt
Classifier: Development Status :: 4 - Beta
Classifier: Programming Language :: Python :: 3.11
Classifier: Programming Language :: Python :: 3.12
Requires-Python: >=3.8
License-File: LICENSE
Requires-Dist: datetime
